charidfield/__init__.py
charidfield/fields.py
django_charid_field-0.6.dist-info/METADATA
django_charid_field-0.6.dist-info/WHEEL
django_charid_field-0.6.dist-info/licenses/LICENSE
django_charid_field-0.6.dist-info/RECORD
