Metadata-Version: 2.4
Name: django-charid-field
Version: 0.6
Summary: Provides a char-based, prefixable ID field for your Django models. Supports cuid, ksuid, ulid, et al.
Project-URL: Repository, https://github.com/yunojuno/django-charid-field
Project-URL: Documentation, https://github.com/yunojuno/django-charid-field/blob/master/README
Author-email: YunoJuno <code@yunojuno.com>
Maintainer-email: YunoJuno <code@yunojuno.com>
License-Expression: MIT
License-File: LICENSE
Classifier: Environment :: Web Environment
Classifier: Framework :: Django :: 5.2
Classifier: Framework :: Django :: 6.0
Classifier: License :: OSI Approved :: MIT License
Classifier: Operating System :: OS Independent
Classifier: Programming Language :: Python :: 3 :: Only
Classifier: Programming Language :: Python :: 3.11
Classifier: Programming Language :: Python :: 3.12
Classifier: Programming Language :: Python :: 3.13
Classifier: Programming Language :: Python :: 3.14
Requires-Python: <4,>=3.11
Requires-Dist: django<7.0,>=5.2
